<?xml version='1.0'?>
<CloneProducts xmlns="http://www.oracle.com" xmlns:xsi="http://www.w3.org/2001/XMLSchema-instance"
xsi:schemaLocation="http://www.oracle.com excludefiles.xsd">

<Product comp="oracle.server">
	<exclude>*.log</exclude>
	<exclude>*.dbf</exclude>
	<exclude>*.aud</exclude>
	<exclude>*.trc</exclude>
	<exclude>EMStagedPatches</exclude>			
	<exclude>sqlnet.ora</exclude>
	<exclude>tnsnames.ora</exclude>
	<exclude>listener.ora</exclude>
	<exclude>oratab</exclude>
</Product>

<Product comp="oracle.client">
	<exclude>*.log</exclude>
	<exclude>sqlnet.ora</exclude>
	<exclude>tnsnames.ora</exclude>
	<exclude>listener.ora</exclude>
</Product>

<Product comp="oracle.crs">
	<exclude>*.log</exclude>
</Product>

<Product comp="oracle.iappserver.iapptop">
	<exclude>centralagents.lst</exclude>
</Product>

<Product comp="oracle.developer.server">
	<exclude>centralagents.lst</exclude>
</Product>

<Product comp="oracle.business.intelligence.as">
	<exclude>centralagents.lst</exclude>
</Product>

<Product comp="oracle.as.j2ee.top">
	<exclude>centralagents.lst</exclude>
</Product>

</CloneProducts>
