<!-- $Header: oracle_workflow.xml 22-jun-2005.16:08:09 krnatara Exp $ -->
<TargetMetadata META_VER="1.2" TYPE="oracle_workflow" RESOURCE_BUNDLE_PACKAGE="oracle.apps.fnd.oam.launchMode.gc.resources">
  <Display>
    <Label NLSID="oracle_wf_name">Oracle Workflow</Label>
  </Display>

<!-- New Response Metric for Oracle Workflow - copied from oracle_database -->
<Metric NAME="Response" TYPE="TABLE">
    <Display>
      <Label NLSID="oracle_workflow_resp">Response</Label>
    </Display>
    <CategoryValue CLASS="Functional" CATEGORY_NAME="FAULT">
    </CategoryValue>
    <TableDescriptor>
      <ColumnDescriptor NAME="userLogon" TYPE="NUMBER" IS_KEY="FALSE">
        <Display FOR_SUMMARY_UI="TRUE">
          <Label NLSID="oracle_workflow_resp_userLogon">User Logon Time (msec)</Label>
          <ShortName NLSID="oracle_workflow_resp_userLogon_short">Logon Time(ms)</ShortName>
        </Display>
      </ColumnDescriptor>
      <ColumnDescriptor NAME="Status" TYPE="NUMBER" IS_KEY="FALSE">
        <Display>
          <Label NLSID="oracle_workflow_resp_status">Status</Label>
        </Display>
      </ColumnDescriptor>
      <ColumnDescriptor NAME="State" TYPE="STRING" IS_KEY="FALSE">
        <Display>
          <Label NLSID="oracle_workflow_resp_state">State</Label>
        </Display>
      </ColumnDescriptor>
      <ColumnDescriptor NAME="oraerr" TYPE="STRING" IS_KEY="FALSE" TRANSIENT="TRUE">
        <Display>
          <Label NLSID="oracle_workflow_resp_oraerr">ORA- Error</Label>
        </Display>
      </ColumnDescriptor>
    </TableDescriptor>
    <QueryDescriptor FETCHLET_ID="OSLineToken">
      <Property NAME="perlBin" SCOPE="SYSTEMGLOBAL">perlBin</Property>
      <Property NAME="scriptsDir" SCOPE="SYSTEMGLOBAL">scriptsDir</Property>
      <Property NAME="command" SCOPE="GLOBAL">
         %perlBin%/perl %scriptsDir%/db/dbresp.pl
      </Property>
      <Property NAME="startsWith" SCOPE="GLOBAL">em_result=</Property>
      <Property NAME="delimiter" SCOPE="GLOBAL">|</Property>
      <Property NAME="ENVEM_TARGET_NAME" SCOPE="INSTANCE">NAME</Property>
      <Property NAME="STDINEM_TARGET_USERNAME" SCOPE="INSTANCE">UserName</Property>
      <Property NAME="STDINEM_TARGET_PASSWORD" SCOPE="INSTANCE">password</Property>
      <Property NAME="MachineName" SCOPE="INSTANCE">MachineName</Property>
      <Property NAME="Port" SCOPE="INSTANCE">Port</Property>
      <Property NAME="SID" SCOPE="INSTANCE">SID</Property>
      <Property NAME="ENVEM_TARGET_ORACLE_HOME" SCOPE="INSTANCE">OracleHome</Property>
      <Property NAME="ENVEM_TARGET_ADDRESS" SCOPE="GLOBAL">(DESCRIPTION=(ADDRESS=(PROTOCOL=TCP)(HOST=%MachineName%)(Port=%Port%))(CONNECT_DATA=(SID=%SID%)))
      </Property>
    </QueryDescriptor>
  </Metric>
 
  <InstanceProperties>
    <InstanceProperty NAME="OracleHome" CREDENTIAL="FALSE" OPTIONAL="FALSE">
      <Display>
        <Label NLSID="oracle_wf_oraclehome_iprop">Machine name</Label>
      </Display>
    </InstanceProperty>
    <InstanceProperty NAME="MachineName" CREDENTIAL="FALSE" OPTIONAL="FALSE">
      <Display>
        <Label NLSID="oracle_wf_machine_iprop">Machine name</Label>
      </Display>
    </InstanceProperty>
    <InstanceProperty NAME="Port" CREDENTIAL="FALSE" OPTIONAL="FALSE">
      <Display>
        <Label NLSID="oracle_wf_port_iprop">Port number</Label>
      </Display>
    </InstanceProperty>
    <InstanceProperty NAME="SID" CREDENTIAL="FALSE" OPTIONAL="FALSE">
      <Display>
        <Label NLSID="oracle_wf_sid_iprop">SID</Label>
      </Display>
    </InstanceProperty>
    <InstanceProperty NAME="UserName" CREDENTIAL="TRUE" OPTIONAL="FALSE" ENCRYPTED="FALSE">
      <Display>
        <Label NLSID="oracle_wf_username_iprop">Schema Username</Label>
      </Display>
    </InstanceProperty>
    <InstanceProperty NAME="password" CREDENTIAL="TRUE" OPTIONAL="FALSE" ENCRYPTED="FALSE">
      <Display>
        <Label NLSID="oracle_wf_password_iprop">Password</Label>
      </Display>
    </InstanceProperty>
  </InstanceProperties>

</TargetMetadata>

