<!DOCTYPE TargetCollection SYSTEM "../dtds/TargetCollection.dtd">
<!-- This file is generated by Collector at 2007-05-02 22:49:43 -->

<TargetCollection TYPE="oracle_forms" INCLUDE_DEFAULT="TRUE">
	<CollectionItem NAME="aggr_FormsResourceUsage" UPLOAD="YES">
		<Schedule>
			<IntervalSchedule INTERVAL="60" TIME_UNIT="Sec"/>
		</Schedule>
		<Condition COLUMN_NAME="cpu.component" CRITICAL="90" WARNING="80" OPERATOR="GE" OCCURRENCES="2" MESSAGE="cpu.component is %value% and has crossed warning (%warning_threshold%) or critical (%critical_threshold%) threshold." MESSAGE_NLSID="cpu_component_cond"/>
		<Condition COLUMN_NAME="totalprivateMem" CRITICAL="90" WARNING="80" OPERATOR="GE" OCCURRENCES="2" MESSAGE="totalprivateMem is %value% and has crossed warning (%warning_threshold%) or critical (%critical_threshold%) threshold." MESSAGE_NLSID="memory_component_cond"/>
	</CollectionItem>
	<CollectionItem NAME="NumberOfSessions" UPLOAD="YES">
		<Schedule>
			<IntervalSchedule INTERVAL="60" TIME_UNIT="Sec"/>
		</Schedule>
		<MetricColl NAME="num">
		</MetricColl>
	</CollectionItem>
        <CollectionItem NAME="Response" UPLOAD="YES">
                <Schedule>
                        <IntervalSchedule INTERVAL="60" TIME_UNIT="Sec"/>
                </Schedule>
                <MetricColl NAME="Response">
                        <Condition COLUMN_NAME="Status" CRITICAL="0" WARNING="NotDefined" OPERATOR="EQ" OCCURRENCES="1" MESSAGE="The Forms instance is not accessible." MESSAGE_NLSID="oracle_sysman_formsserver_Fstatus"/>
                </MetricColl>
        </CollectionItem>
        <CollectionItem NAME="servlet_rollup" UPLOAD="YES">
                <Schedule>
                        <IntervalSchedule INTERVAL="60" TIME_UNIT="Sec"/>
                </Schedule>
                        <Condition COLUMN_NAME="service.averageTime" CRITICAL="1000" WARNING="500" OPERATOR="GT" OCCURRENCES="1" MESSAGE="The Forms Listener response time is unacceptable." MESSAGE_NLSID="oracle_sysman_formsserver_Uresponsetime"/>
        </CollectionItem>
</TargetCollection>
