<!-- This file is generated by Collector at 2007-02-01 03:21:48 -->

<TargetCollection TYPE="oracle_bam_web" INCLUDE_DEFAULT="TRUE">

	<CollectionItem NAME="BAM_server_reportserver_activity_rate" UPLOAD="YES">
		<Schedule>
			<IntervalSchedule INTERVAL="300" TIME_UNIT="Sec"/>
		</Schedule>
		<MetricColl NAME="BAM_server_reportserver_activity_rate">
		</MetricColl>
	</CollectionItem>

	<CollectionItem NAME="BAM_server_reportserver_activedataviewset" UPLOAD="YES">
		<Schedule>
			<IntervalSchedule INTERVAL="300" TIME_UNIT="Sec"/>
		</Schedule>
		<MetricColl NAME="BAM_server_reportserver_activedataviewset">
		</MetricColl>
	</CollectionItem>

	<CollectionItem NAME="BAM_server_reportserver_activedatapageinfo" UPLOAD="YES">
		<Schedule>
			<IntervalSchedule INTERVAL="300" TIME_UNIT="Sec"/>
		</Schedule>
		<MetricColl NAME="BAM_server_reportserver_activedatapageinfo">
		</MetricColl>
	</CollectionItem>

	<CollectionItem NAME="BAM_server_reportserver_activedatapage" UPLOAD="YES">
		<Schedule>
			<IntervalSchedule INTERVAL="300" TIME_UNIT="Sec"/>
		</Schedule>
		<MetricColl NAME="BAM_server_reportserver_activedatapage">
		</MetricColl>
	</CollectionItem>

</TargetCollection>
