<?xml version="1.0" encoding="UTF-8"?>
<object-persistence xmlns="http://www.eclipse.org/eclipselink/xsds/persistence" xmlns:xsd="http://www.w3.org/2001/XMLSchema" xmlns:eclipselink="http://www.eclipse.org/eclipselink/xsds/persistence" xmlns:xsi="http://www.w3.org/2001/XMLSchema-instance" version="Eclipse Persistence Services - 2.3.1.v20111018-r10243">
   <name>CreateEmailRecord-OR</name>
   <class-mapping-descriptors>
      <class-mapping-descriptor xsi:type="object-relational-class-mapping-descriptor">
         <class>CreateEmailRecord.TbEmailDetails</class>
         <alias>TB_EMAIL_DETAILS</alias>
         <primary-key>
            <field table="TB_EMAIL_DETAILS" name="OSB_TRANSACTION_ID" xsi:type="column"/>
         </primary-key>
         <events/>
         <querying>
            <queries>
               <query name="CreateEmailRecordSelect" xsi:type="read-all-query">
                  <reference-class>CreateEmailRecord.TbEmailDetails</reference-class>
                  <container xsi:type="list-container-policy">
                     <collection-type>java.util.Vector</collection-type>
                  </container>
               </query>
            </queries>
            <timeout>10</timeout>
         </querying>
         <attribute-mappings>
            <attribute-mapping xsi:type="direct-mapping">
               <attribute-name>osbTransactionId</attribute-name>
               <field table="TB_EMAIL_DETAILS" name="OSB_TRANSACTION_ID" xsi:type="column"/>
               <attribute-classification>java.lang.String</attribute-classification>
            </attribute-mapping>
            <attribute-mapping xsi:type="direct-mapping">
               <attribute-name>channelName</attribute-name>
               <field table="TB_EMAIL_DETAILS" name="CHANNEL_NAME" xsi:type="column"/>
               <attribute-classification>java.lang.String</attribute-classification>
            </attribute-mapping>
            <attribute-mapping xsi:type="direct-mapping">
               <attribute-name>profileId</attribute-name>
               <field table="TB_EMAIL_DETAILS" name="PROFILE_ID" xsi:type="column"/>
               <attribute-classification>java.lang.String</attribute-classification>
            </attribute-mapping>
            <attribute-mapping xsi:type="direct-mapping">
               <attribute-name>priority</attribute-name>
               <field table="TB_EMAIL_DETAILS" name="PRIORITY" xsi:type="column"/>
               <attribute-classification>java.math.BigDecimal</attribute-classification>
            </attribute-mapping>
            <attribute-mapping xsi:type="direct-mapping">
               <attribute-name>format</attribute-name>
               <field table="TB_EMAIL_DETAILS" name="FORMAT" xsi:type="column"/>
               <attribute-classification>java.lang.String</attribute-classification>
            </attribute-mapping>
            <attribute-mapping xsi:type="direct-mapping">
               <attribute-name>recEmailid</attribute-name>
               <field table="TB_EMAIL_DETAILS" name="REC_EMAILID" xsi:type="column"/>
               <attribute-classification>java.lang.String</attribute-classification>
            </attribute-mapping>
            <attribute-mapping xsi:type="direct-mapping">
               <attribute-name>ccEmailid</attribute-name>
               <field table="TB_EMAIL_DETAILS" name="CC_EMAILID" xsi:type="column"/>
               <attribute-classification>java.lang.String</attribute-classification>
            </attribute-mapping>
            <attribute-mapping xsi:type="direct-mapping">
               <attribute-name>bccEmailid</attribute-name>
               <field table="TB_EMAIL_DETAILS" name="BCC_EMAILID" xsi:type="column"/>
               <attribute-classification>java.lang.String</attribute-classification>
            </attribute-mapping>
            <attribute-mapping xsi:type="direct-mapping">
               <attribute-name>subject</attribute-name>
               <field table="TB_EMAIL_DETAILS" name="SUBJECT" xsi:type="column"/>
               <attribute-classification>java.lang.String</attribute-classification>
            </attribute-mapping>
            <attribute-mapping xsi:type="direct-mapping">
               <attribute-name>body</attribute-name>
               <field table="TB_EMAIL_DETAILS" name="BODY" xsi:type="column"/>
               <attribute-classification>java.lang.String</attribute-classification>
            </attribute-mapping>
            <attribute-mapping xsi:type="direct-mapping">
               <attribute-name>senderEmailid</attribute-name>
               <field table="TB_EMAIL_DETAILS" name="SENDER_EMAILID" xsi:type="column"/>
               <attribute-classification>java.lang.String</attribute-classification>
            </attribute-mapping>
            <attribute-mapping xsi:type="direct-mapping">
               <attribute-name>channelTransactionId</attribute-name>
               <field table="TB_EMAIL_DETAILS" name="CHANNEL_TRANSACTION_ID" xsi:type="column"/>
               <attribute-classification>java.lang.String</attribute-classification>
            </attribute-mapping>
            <attribute-mapping xsi:type="direct-mapping">
               <attribute-name>notificationId</attribute-name>
               <field table="TB_EMAIL_DETAILS" name="NOTIFICATION_ID" xsi:type="column"/>
               <attribute-classification>java.lang.String</attribute-classification>
            </attribute-mapping>
            <attribute-mapping xsi:type="direct-mapping">
               <attribute-name>status</attribute-name>
               <field table="TB_EMAIL_DETAILS" name="STATUS" xsi:type="column"/>
               <attribute-classification>java.math.BigDecimal</attribute-classification>
            </attribute-mapping>
            <attribute-mapping xsi:type="direct-mapping">
               <attribute-name>created</attribute-name>
               <field table="TB_EMAIL_DETAILS" name="CREATED" xsi:type="column"/>
               <attribute-classification>java.sql.Timestamp</attribute-classification>
            </attribute-mapping>
            <attribute-mapping xsi:type="direct-mapping">
               <attribute-name>lastUpdated</attribute-name>
               <field table="TB_EMAIL_DETAILS" name="LAST_UPDATED" xsi:type="column"/>
               <attribute-classification>java.sql.Timestamp</attribute-classification>
            </attribute-mapping>
            <attribute-mapping xsi:type="direct-mapping">
               <attribute-name>statusMessage</attribute-name>
               <field table="TB_EMAIL_DETAILS" name="STATUS_MESSAGE" xsi:type="column"/>
               <attribute-classification>java.lang.String</attribute-classification>
            </attribute-mapping>
            <attribute-mapping xsi:type="direct-mapping">
               <attribute-name>lang</attribute-name>
               <field table="TB_EMAIL_DETAILS" name="LANG" xsi:type="column"/>
               <attribute-classification>java.lang.String</attribute-classification>
            </attribute-mapping>
            <attribute-mapping xsi:type="direct-mapping">
               <attribute-name>retryCnt</attribute-name>
               <field table="TB_EMAIL_DETAILS" name="RETRY_CNT" xsi:type="column"/>
               <attribute-classification>java.lang.Integer</attribute-classification>
            </attribute-mapping>
         </attribute-mappings>
         <descriptor-type>independent</descriptor-type>
         <caching>
            <cache-type>weak-reference</cache-type>
            <cache-size>-1</cache-size>
            <always-refresh>true</always-refresh>
         </caching>
         <remote-caching>
            <cache-type>weak-reference</cache-type>
            <cache-size>-1</cache-size>
         </remote-caching>
         <instantiation/>
         <copying xsi:type="instantiation-copy-policy"/>
         <tables>
            <table name="TB_EMAIL_DETAILS"/>
         </tables>
         <structure>structureName</structure>
      </class-mapping-descriptor>
   </class-mapping-descriptors>
   <login xsi:type="database-login">
      <platform-class>org.eclipse.persistence.platform.database.oracle.Oracle9Platform</platform-class>
      <connection-url></connection-url>
   </login>
</object-persistence>